cone.ugm-1.0a7-nspkg.pth
cone/ugm/__init__.py
cone/ugm/events.py
cone/ugm/localmanager.py
cone/ugm/settings.py
cone/ugm/utils.py
cone/ugm/browser/__init__.py
cone/ugm/browser/actions.py
cone/ugm/browser/authoring.py
cone/ugm/browser/autoincrement.py
cone/ugm/browser/columns.py
cone/ugm/browser/expires.py
cone/ugm/browser/group.py
cone/ugm/browser/groups.py
cone/ugm/browser/listing.py
cone/ugm/browser/password.py
cone/ugm/browser/portrait.py
cone/ugm/browser/principal.py
cone/ugm/browser/remote.py
cone/ugm/browser/roles.py
cone/ugm/browser/root.py
cone/ugm/browser/settings.py
cone/ugm/browser/user.py
cone/ugm/browser/users.py
cone/ugm/browser/utils.py
cone/ugm/browser/forms/general_settings.yaml
cone/ugm/browser/forms/localmanager_settings.yaml
cone/ugm/browser/static/styles.css
cone/ugm/browser/static/ugm.js
cone/ugm/browser/static/images/default_portrait.jpg
cone/ugm/browser/templates/column_listing.pt
cone/ugm/browser/templates/columns.pt
cone/ugm/browser/templates/general_settings.pt
cone/ugm/browser/templates/localmanager_settings.pt
cone/ugm/browser/templates/principal_left_column.pt
cone/ugm/browser/templates/principal_right_column.pt
cone/ugm/browser/templates/principals_left_column.pt
cone/ugm/browser/templates/principals_right_column.pt
cone/ugm/locale/cone.ugm.pot
cone/ugm/locale/de/LC_MESSAGES/cone.ugm.mo
cone/ugm/locale/de/LC_MESSAGES/cone.ugm.po
cone/ugm/locale/en/LC_MESSAGES/cone.ugm.mo
cone/ugm/locale/en/LC_MESSAGES/cone.ugm.po
cone/ugm/model/__init__.py
cone/ugm/model/group.py
cone/ugm/model/groups.py
cone/ugm/model/user.py
cone/ugm/model/users.py
cone/ugm/testing/__init__.py
cone/ugm/testing/localmanager.xml
cone/ugm/testing/ugm.xml
cone/ugm/tests/__init__.py
cone/ugm/tests/test_browser_actions.py
cone/ugm/tests/test_browser_autoincrement.py
cone/ugm/tests/test_browser_expires.py
cone/ugm/tests/test_browser_group.py
cone/ugm/tests/test_browser_groups.py
cone/ugm/tests/test_browser_password.py
cone/ugm/tests/test_browser_portrait.py
cone.ugm-1.0a7.dist-info/LICENSE.rst
cone.ugm-1.0a7.dist-info/METADATA
cone.ugm-1.0a7.dist-info/WHEEL
cone.ugm-1.0a7.dist-info/namespace_packages.txt
cone.ugm-1.0a7.dist-info/top_level.txt
cone.ugm-1.0a7.dist-info/RECORD
