Metadata-Version: 2.1
Name: cone.ugm
Version: 1.0a7
Summary: User and group management
Home-page: http://github.com/conestack/cone.ugm
Author: Cone Contributors
Author-email: dev@conestack.org
License: LGPLv3
Platform: UNKNOWN
Classifier: Environment :: Web Environment
Classifier: Programming Language :: Python
Classifier: Topic :: Internet :: WWW/HTTP :: Dynamic Content
Classifier: License :: OSI Approved :: GNU Lesser General Public License v3 (LGPLv3)
Requires-Dist: Pillow
Requires-Dist: cone.app[lxml] (>=1.0.3)
Requires-Dist: natsort
Requires-Dist: setuptools
Requires-Dist: yafowil.widget.array
Requires-Dist: yafowil.widget.autocomplete
Requires-Dist: yafowil.widget.datetime
Requires-Dist: yafowil.widget.dict
Requires-Dist: yafowil.widget.image
Requires-Dist: yafowil.yaml
Provides-Extra: test
Requires-Dist: zope.testrunner ; extra == 'test'
